runman/__init__.py
runman/runman.py
runman/tests/__init__.py
runman/tests/test_runman.py
runman-0.2.1.dist-info/LICENSE
runman-0.2.1.dist-info/METADATA
runman-0.2.1.dist-info/WHEEL
runman-0.2.1.dist-info/top_level.txt
runman-0.2.1.dist-info/RECORD
